lanelet2anchors/__init__.py
lanelet2anchors/anchor_generator.py
lanelet2anchors/anchor_generation/__init__.py
lanelet2anchors/anchor_generation/anchor.py
lanelet2anchors/anchor_generation/create_anchors_from_lanelet.py
lanelet2anchors/anchor_generation/discover_anchors.py
lanelet2anchors/anchor_generation/sort_anchors.py
lanelet2anchors/anchor_tools/__init__.py
lanelet2anchors/anchor_tools/anchor2linestring.py
lanelet2anchors/anchor_tools/anchor2polygon.py
lanelet2anchors/anchor_tools/interpolate_lanelet.py
lanelet2anchors/anchor_tools/lanelet_matching.py
lanelet2anchors/anchor_tools/nusc.py
lanelet2anchors/anchor_tools/plot_car.py
lanelet2anchors/anchor_tools/vehicle_ahead.py
lanelet2anchors/anchor_tools/visualize.py
lanelet2anchors-0.1.0.dist-info/METADATA
lanelet2anchors-0.1.0.dist-info/WHEEL
lanelet2anchors-0.1.0.dist-info/RECORD
