Metadata-Version: 2.1
Name: lanelet2anchors
Version: 0.1.0
Summary: Easy anchor generation for autonomous driving based on Lanelet2 maps
Project-URL: Homepage, https://github.com/FelixHertlein/lanelet2anchors
Project-URL: Bug Tracker, https://github.com/FelixHertlein/lanelet2anchors/issues
Author-email: Alexander Naumann <alex.code@mail.com>, Felix Hertlein <hertlein.research@gmail.com>
Classifier: License :: Free for non-commercial use
Classifier: Operating System :: POSIX :: Linux
Classifier: Programming Language :: Python :: 3
Requires-Python: >=3.8
Requires-Dist: fastdtw<1,>=0.3.4
Requires-Dist: lanelet2<2,>=1.2.1
Requires-Dist: networkx<3,>=2.8.8
Requires-Dist: scipy<2,>=1.10.1
Requires-Dist: shapely<2,>=1.8.5
Provides-Extra: dev
Requires-Dist: black[jupyter]<24,>=23.3.0; extra == 'dev'
Requires-Dist: ipykernel<7,>=6.23.2; extra == 'dev'
Requires-Dist: isort<6,>=5.12.0; extra == 'dev'
Requires-Dist: mypy<2,>=1.3.0; extra == 'dev'
Requires-Dist: nuscenes-devkit<2,>=1.1.10; extra == 'dev'
Requires-Dist: pre-commit<4,>=3.3.3; extra == 'dev'
Provides-Extra: docs
Requires-Dist: jupyter-contrib-nbextensions; extra == 'docs'
Requires-Dist: mkdocs; extra == 'docs'
Requires-Dist: mkdocs-bibtex; extra == 'docs'
Requires-Dist: mkdocs-jupyter; extra == 'docs'
Requires-Dist: mkdocstrings[python]; extra == 'docs'
